{
    "name": "Ancient Amethyst Dragon (FTD)",
    "size": "Gargantuan",
    "type": "Dragon (Gem)",
    "alignment": "neutral",
    "AC": "20 (natural armor)",
    "HP": "444 (24d20 + 192)",
    "CR": "23 (XP 50,000, or 62,000 in lair; PB +7)",
    "init": "+2",
    "speed": "40 ft., Fly 80 ft. (hover), Swim 40 ft.",
    "STR": "26",
    "DEX": "14",
    "CON": "27",
    "INT": "26",
    "WIS": "19",
    "CHA": "23",
    "saves": "Dex +9, Con +15, Wis +11, Cha +13",
    "skills": "Arcana +22, Perception +18, Persuasion +13, Stealth +9",
    "dmg_vuln": "",
    "dmg_resist": "force, psychic",
    "dmg_immun": "",
    "cond_immun": "frightened, prone",
    "senses": "Blindsight 60 ft., Darkvision 120 ft., passive Perception 28",
    "languages": "Common, Draconic, telepathy 120 ft.",
    "environment": "",
    "treasure": "",
    "link": "https://5e.tools/bestiary/ancient-amethyst-dragon-ftd.html"
}